logitech_steering_wheel/__init__.py
logitech_steering_wheel/_controllerproperties.py
logitech_steering_wheel/_enums.py
logitech_steering_wheel/_state.py
logitech_steering_wheel/_wrapper.py
logitech_steering_wheel-1.0.data/data/lib/site-packages/logitech_steering_wheel/lib/x64/LogitechSteeringWheelEnginesWrapper.dll
logitech_steering_wheel-1.0.data/data/lib/site-packages/logitech_steering_wheel/lib/x86/LogitechSteeringWheelEnginesWrapper.dll
logitech_steering_wheel-1.0.dist-info/LICENSE
logitech_steering_wheel-1.0.dist-info/METADATA
logitech_steering_wheel-1.0.dist-info/WHEEL
logitech_steering_wheel-1.0.dist-info/top_level.txt
logitech_steering_wheel-1.0.dist-info/RECORD
