Metadata-Version: 2.1
Name: logitech-steering-wheel
Version: 1.0
Summary: A wrapper to use the Logitech Steering Wheel SDK in Python
Home-page: https://github.com/tud-hri/logitech_steering_wheel
Author: O. Siebinga
Author-email: o.siebinga@tudelft.nl
License: MIT License
Project-URL: Bug Tracker, https://github.com/tud-hri/logitech_steering_wheel/issues
Platform: UNKNOWN
Classifier: Programming Language :: Python :: 3
Classifier: License :: OSI Approved :: MIT License
Classifier: Operating System :: Microsoft :: Windows
License-File: LICENSE
